podcasts/__init__.py
podcasts/api.py
podcasts/constants.py
podcasts/episode_worker.py
podcasts/episodes_driver.py
podcasts/itunes.py
podcasts/log.py
podcasts/series_crawler.py
podcasts/series_driver.py
podcasts/series_worker.py
podcasts/site_crawler.py
podcasts/models/__init__.py
podcasts/models/entity.py
podcasts/models/episode.py
podcasts/models/series.py
podcasts/storers/__init__.py
podcasts/storers/json_storer.py
podcasts/storers/storer.py
podcasts/tests/__init__.py
py_podcast-1.0.7.dist-info/DESCRIPTION.rst
py_podcast-1.0.7.dist-info/METADATA
py_podcast-1.0.7.dist-info/RECORD
py_podcast-1.0.7.dist-info/WHEEL
py_podcast-1.0.7.dist-info/metadata.json
py_podcast-1.0.7.dist-info/top_level.txt
